pygris/__init__.py
pygris/data.py
pygris/enumeration_units.py
pygris/geocode.py
pygris/geometry.py
pygris/helpers.py
pygris/internal_data.py
pygris/legislative.py
pygris/metro_areas.py
pygris/national.py
pygris/native.py
pygris/transportation.py
pygris/utils.py
pygris/water.py
pygris/internals/__init__.py
pygris/internals/fips_codes.csv
pygris-0.2.1.dist-info/licenses/LICENSE
pygris-0.2.1.dist-info/METADATA
pygris-0.2.1.dist-info/WHEEL
pygris-0.2.1.dist-info/top_level.txt
pygris-0.2.1.dist-info/RECORD
