Metadata-Version: 2.4
Name: pygris
Version: 0.2.1
Summary: Download and use US Census Bureau TIGER/Line Shapefiles and other data resources in Python
Author-email: Kyle Walker <kyle@walker-data.com>
Project-URL: Homepage, https://github.com/walkerke/pygris
Project-URL: Bug Tracker, https://github.com/walkerke/pygris/issues
Classifier: Programming Language :: Python :: 3
Classifier: Operating System :: OS Independent
Classifier: License :: OSI Approved :: MIT License
Requires-Python: >=3.7
License-File: LICENSE
Requires-Dist: geopandas>=0.9
Requires-Dist: requests
Requires-Dist: platformdirs
Provides-Extra: explore
Requires-Dist: mapclassify; extra == "explore"
Requires-Dist: ipyleaflet; extra == "explore"
Requires-Dist: folium; extra == "explore"
Dynamic: license-file
